[
  {
    "id": 100,
    "content": "morning task",
    "date": 1679443200000,
    "slot": 0,
    "TimerTicks": [
      {
        "id": 400,
        "userId": 1,
        "date": 1679443200000,
        "tickNumber": 40,
        "distracted": 0,
        "summaryId": 100
      }
    ]
  },
  {
    "id": 101,
    "content": "afternoon task",
    "date": 1679443200000,
    "slot": 1,
    "TimerTicks": [
      {
        "id": 401,
        "userId": 1,
        "date": 1679443200000,
        "tickNumber": 56,
        "distracted": 1,
        "summaryId": 101
      }
    ]
  }
]
